switchcase_demo/__init__.py
switchcase_demo/switchcase.py
switch_case_demo-0.0.1.dist-info/LICENSE
switch_case_demo-0.0.1.dist-info/METADATA
switch_case_demo-0.0.1.dist-info/WHEEL
switch_case_demo-0.0.1.dist-info/top_level.txt
switch_case_demo-0.0.1.dist-info/RECORD
