Metadata-Version: 2.1
Name: switch-case-demo
Version: 0.0.1
Summary: A sample python package to implement switch case in python
Author: Tuan Nguyen
Author-email: nguyenquotuan02011992@gmail.om
Classifier: Programming Language :: Python :: 3
Classifier: License :: OSI Approved :: MIT License
Classifier: Operating System :: OS Independent
Requires-Python: >=3.7
License-File: LICENSE
